alertmanagermeshtastic/__init__.py
alertmanagermeshtastic/cli.py
alertmanagermeshtastic/config.py
alertmanagermeshtastic/http.py
alertmanagermeshtastic/meshtastic.py
alertmanagermeshtastic/processor.py
alertmanagermeshtastic/signals.py
alertmanagermeshtastic/tokencli.py
alertmanagermeshtastic/util.py
alertmanagermeshtastic-2025.8.10.1.dist-info/licenses/LICENSE
alertmanagermeshtastic-2025.8.10.1.dist-info/METADATA
alertmanagermeshtastic-2025.8.10.1.dist-info/WHEEL
alertmanagermeshtastic-2025.8.10.1.dist-info/entry_points.txt
alertmanagermeshtastic-2025.8.10.1.dist-info/top_level.txt
alertmanagermeshtastic-2025.8.10.1.dist-info/RECORD
