Metadata-Version: 2.4
Name: alertmanagermeshtastic
Version: 2025.8.10.1
Summary: A proxy to forward messages received via HTTP to MESHTASTIC
Home-page: https://github.com/Apfelwurm/alertmanagermeshtastic
Author: Alexander Volz
Author-email: github@volzit.de
License: MIT
Project-URL: Source code, https://github.com/Apfelwurm/alertmanagermeshtastic
Project-URL: Changelog, https://github.com/Apfelwurm/alertmanagermeshtastic/releases
Keywords: meshtastic,webhook
Platform: any
Classifier: Intended Audience :: Developers
Classifier: Intended Audience :: Other Audience
Classifier: Intended Audience :: System Administrators
Classifier: License :: OSI Approved :: MIT License
Classifier: Operating System :: OS Independent
Classifier: Programming Language :: Python
Classifier: Programming Language :: Python :: 3
Classifier: Programming Language :: Python :: 3 :: Only
Classifier: Programming Language :: Python :: 3.9
Classifier: Programming Language :: Python :: 3.10
Classifier: Programming Language :: Python :: 3.11
Classifier: Programming Language :: Python :: 3.12
Classifier: Programming Language :: Python :: 3.13
Classifier: Topic :: Communications :: Chat :: Internet Relay Chat
Classifier: Topic :: Internet :: WWW/HTTP
Classifier: Topic :: System :: Logging
Classifier: Topic :: System :: Systems Administration
Classifier: Topic :: Utilities
Requires-Python: >=3.9
License-File: LICENSE
Requires-Dist: blinker==1.9.0
Requires-Dist: meshtastic==2.6.4
Requires-Dist: rtoml==0.12.0
Requires-Dist: werkzeug==3.1.3
Requires-Dist: python-dateutil==2.9.0.post0
Dynamic: license-file
